edict/__init__.py
edict/cli.py
edict/edict.jar
edict/simulate.py
edict_iot-1.0.0.dist-info/METADATA
edict_iot-1.0.0.dist-info/WHEEL
edict_iot-1.0.0.dist-info/entry_points.txt
edict_iot-1.0.0.dist-info/top_level.txt
edict_iot-1.0.0.dist-info/RECORD
