Metadata-Version: 2.4
Name: edict-iot
Version: 1.0.0
Summary: Simulator for IoT data flow performance
Author-email: Houssam Hajj Hassan <houssam.hajj_hassan@telecom-sudparis.eu>
License-Expression: MIT
Project-URL: Homepage, https://github.com/houssamhh/edict
Classifier: Programming Language :: Python :: 3
Classifier: Operating System :: OS Independent
Requires-Python: >=3.7
